benchmark/hs-tool.py
benchmark/benchmark.py
benchmark/benchmarks.txt
benchmark/mhindex.py
benchmark/sortbench.py
benchmark/__init__.py
benchmark/intersection.py
benchmark/wordstats.py
hypatia/__init__.py
hypatia/interfaces.py
hypatia/text/stopdict.py
hypatia/text/setops.py
hypatia/text/textindex.txt
hypatia/text/cosineindex.py
hypatia/text/queryparser.py
hypatia/text/okapiindex.py
hypatia/text/parsetree.py
hypatia/text/baseindex.py
hypatia/text/__init__.py
hypatia/text/widcode.py
hypatia/text/okascore.c
hypatia/text/okascore.cpython-39-i386-linux-gnu.so
hypatia/text/htmlsplitter.py
hypatia/text/interfaces.py
hypatia/text/lexicon.py
hypatia/text/tests/test_index.py
hypatia/text/tests/test_lexicon.py
hypatia/text/tests/test_parsetree.py
hypatia/text/tests/test_baseindex.py
hypatia/text/tests/test_htmlsplitter.py
hypatia/text/tests/test_cosineindex.py
hypatia/text/tests/test_setops.py
hypatia/text/tests/__init__.py
hypatia/text/tests/test_okapiindex.py
hypatia/text/tests/test_queryengine.py
hypatia/text/tests/test_queryparser.py
hypatia/text/tests/test_widcode.py
hypatia/text/tests/test_textindex.py
hypatia/keyword/__init__.py
hypatia/keyword/tests.py
hypatia/keyword/interfaces.py
hypatia/field/__init__.py
hypatia/field/README.txt
hypatia/field/tests.py
hypatia/query/__init__.py
hypatia/query/tests.py
hypatia/nbest/__init__.py
hypatia/nbest/tests.py
hypatia/nbest/interfaces.py
hypatia/exc/__init__.py
hypatia/exc/tests.py
hypatia/tests/test_functional.py
hypatia/tests/__init__.py
hypatia/facet/__init__.py
hypatia/facet/tests.py
hypatia/util/__init__.py
hypatia/util/tests.py
hypatia/catalog/__init__.py
hypatia/catalog/tests.py
hypatia-0.5.dist-info/top_level.txt
hypatia-0.5.dist-info/RECORD
hypatia-0.5.dist-info/LICENSE.txt
hypatia-0.5.dist-info/METADATA
hypatia-0.5.dist-info/WHEEL
