Metadata-Version: 2.1
Name: hypatia
Version: 0.5
Summary: Python package for searching and indexing
Home-page: http://pylonsproject.org
Author: Zope Foundation and Contributors
Author-email: pylons-discuss@googlegroups.com
License: ZPL 2.1
Keywords: indexing catalog search
Classifier: Intended Audience :: Developers
Classifier: Programming Language :: Python
Classifier: Programming Language :: Python :: 3.8
Classifier: Programming Language :: Python :: 3.9
Classifier: Programming Language :: Python :: 3.10
Classifier: Programming Language :: Python :: 3.11
Classifier: Programming Language :: Python :: 3.12
Classifier: Programming Language :: Python :: 3.13
Classifier: Programming Language :: Python :: Implementation :: CPython
Classifier: Programming Language :: Python :: Implementation :: PyPy
Classifier: Topic :: Internet :: WWW/HTTP :: Indexing/Search
License-File: LICENSE.txt
Requires-Dist: persistent
Requires-Dist: BTrees
Requires-Dist: ZODB>=4.0.0b2
Requires-Dist: zope.interface
Provides-Extra: benchmark
Requires-Dist: PyChart; extra == "benchmark"
Provides-Extra: testing
Requires-Dist: pytest; extra == "testing"
Requires-Dist: coverage; extra == "testing"
Provides-Extra: docs
Requires-Dist: Sphinx>=3.0.0; extra == "docs"
Requires-Dist: docutils; extra == "docs"
Requires-Dist: pylons-sphinx-themes>=1.0.8; extra == "docs"
